pantsmud
