Metadata-Version: 1.1
Name: pantsmud
Version: 0.4.0
Summary: A simple MUD library built using the Pants networking framework.
Home-page: http://github.com/ecdavis/pantsmud
Author: ecdavis
Author-email: me@ezdwt.com
License: UNKNOWN
Download-URL: https://github.com/ecdavis/pantsmud/tarball/master
Platform: UNKNOWN
Classifier: Programming Language :: Python :: 2.7
Classifier: License :: OSI Approved :: Apache Software License
Classifier: Operating System :: OS Independent
Classifier: Environment :: Other Environment
Classifier: Intended Audience :: Developers
Classifier: Natural Language :: English
